iktomi/__init__.py
iktomi/auth.py
iktomi/storage.py
iktomi/cli/__init__.py
iktomi/cli/app.py
iktomi/cli/base.py
iktomi/cli/fcgi.py
iktomi/cli/lazy.py
iktomi/cli/sqla.py
iktomi/db/__init__.py
iktomi/db/files.py
iktomi/db/sqla/__init__.py
iktomi/db/sqla/declarative.py
iktomi/db/sqla/files.py
iktomi/db/sqla/images.py
iktomi/db/sqla/types.py
iktomi/forms/__init__.py
iktomi/forms/convs.py
iktomi/forms/fields.py
iktomi/forms/files.py
iktomi/forms/form.py
iktomi/forms/perms.py
iktomi/forms/shortcuts.py
iktomi/forms/widgets.py
iktomi/templates/__init__.py
iktomi/templates/jinja2/__init__.py
iktomi/templates/jinja2/templates/forms/default.html
iktomi/templates/jinja2/templates/forms/table.html
iktomi/templates/jinja2/templates/media/css_inline.html
iktomi/templates/jinja2/templates/media/css_ref.html
iktomi/templates/jinja2/templates/media/js_inline.html
iktomi/templates/jinja2/templates/media/js_ref.html
iktomi/templates/jinja2/templates/widgets/checkbox.html
iktomi/templates/jinja2/templates/widgets/fieldlist.html
iktomi/templates/jinja2/templates/widgets/fieldset.html
iktomi/templates/jinja2/templates/widgets/file.html
iktomi/templates/jinja2/templates/widgets/hiddeninput.html
iktomi/templates/jinja2/templates/widgets/passwordinput.html
iktomi/templates/jinja2/templates/widgets/select-checkbox.html
iktomi/templates/jinja2/templates/widgets/select.html
iktomi/templates/jinja2/templates/widgets/span.html
iktomi/templates/jinja2/templates/widgets/textarea.html
iktomi/templates/jinja2/templates/widgets/textinput.html
iktomi/unstable/__init__.py
iktomi/unstable/db/__init__.py
iktomi/unstable/db/files.py
iktomi/unstable/db/sqla/__init__.py
iktomi/unstable/db/sqla/factories.py
iktomi/unstable/db/sqla/files.py
iktomi/unstable/db/sqla/images.py
iktomi/unstable/db/sqla/mixin.py
iktomi/unstable/db/sqla/public_query.py
iktomi/unstable/db/sqla/replication.py
iktomi/unstable/forms/__init__.py
iktomi/unstable/forms/convs.py
iktomi/unstable/forms/files.py
iktomi-0.11.dist-info/AUTHORS
iktomi-0.11.dist-info/LICENSE.txt
iktomi-0.11.dist-info/METADATA
iktomi-0.11.dist-info/WHEEL
iktomi-0.11.dist-info/dependency_links.txt
iktomi-0.11.dist-info/top_level.txt
iktomi-0.11.dist-info/RECORD
